contrail/__init__.py
contrail/security/__init__.py
contrail/security/onlineca/__init__.py
contrail/security/onlineca/client/LICENSE
contrail/security/onlineca/client/__init__.py
contrail/security/onlineca/client/cli.py
contrail/security/onlineca/client/openssl_utils.py
contrail/security/onlineca/client/sh/__init__.py
contrail/security/onlineca/client/sh/onlineca-get-cert-wget.sh
contrail/security/onlineca/client/sh/onlineca-get-cert.sh
contrail/security/onlineca/client/sh/onlineca-get-trustroots-wget.sh
contrail/security/onlineca/client/sh/onlineca-get-trustroots.sh
contrail/security/onlineca/client/test/__init__.py
contrail/security/onlineca/client/test/localhost.crt
contrail/security/onlineca/client/test/localhost.key
contrail/security/onlineca/client/test/test_cli.py
contrail/security/onlineca/client/test/test_client.py
contrail/security/onlineca/client/test/test_onlineca_client-local.cfg
contrail/security/onlineca/client/test/test_onlineca_client.cfg
contrail/security/onlineca/client/test/usercert.pem
contrail/security/onlineca/client/test/ca/0084963c.0
contrail/security/onlineca/client/test/ca/0119347c.0
contrail/security/onlineca/client/test/ca/01bba7cf.0
contrail/security/onlineca/client/test/ca/02265526.0
contrail/security/onlineca/client/test/ca/02b2d53d.0
contrail/security/onlineca/client/test/ca/02e7f0f4.0
contrail/security/onlineca/client/test/ca/053e3ae0.0
contrail/security/onlineca/client/test/ca/0597e90c.0
contrail/security/onlineca/client/test/ca/064e0aa9.0
contrail/security/onlineca/client/test/ca/06c34218.0
contrail/security/onlineca/client/test/ca/09184877.0
contrail/security/onlineca/client/test/ca/0d66c1c3.0
contrail/security/onlineca/client/test/ca/12d0da68.0
contrail/security/onlineca/client/test/ca/1445ed77.0
contrail/security/onlineca/client/test/ca/157753a5.0
contrail/security/onlineca/client/test/ca/159117b6.0
contrail/security/onlineca/client/test/ca/1c3f2ca8.0
contrail/security/onlineca/client/test/ca/1d1427de.0
ContrailOnlineCAClient-0.5.1.dist-info/METADATA
ContrailOnlineCAClient-0.5.1.dist-info/WHEEL
ContrailOnlineCAClient-0.5.1.dist-info/entry_points.txt
ContrailOnlineCAClient-0.5.1.dist-info/top_level.txt
ContrailOnlineCAClient-0.5.1.dist-info/RECORD
