Metadata-Version: 2.1
Name: ContrailOnlineCAClient
Version: 0.5.1
Summary: Certificate Authority web service client
Home-page: https://github.com/cedadev/online_ca_client
Author: Philip Kershaw
Author-email: Philip.Kershaw@stfc.ac.uk
Maintainer: Philip Kershaw
Maintainer-email: Philip.Kershaw@stfc.ac.uk
License: BSD - See LICENSE file in contrail.security.onlineca.client
Platform: POSIX
Platform: Linux
Platform: Windows
Classifier: Development Status :: 5 - Production/Stable
Classifier: Environment :: Console
Classifier: Environment :: Web Environment
Classifier: Intended Audience :: End Users/Desktop
Classifier: Intended Audience :: Developers
Classifier: Intended Audience :: System Administrators
Classifier: Intended Audience :: Science/Research
Classifier: License :: OSI Approved :: BSD License
Classifier: Natural Language :: English
Classifier: Operating System :: Microsoft :: Windows
Classifier: Operating System :: POSIX :: Linux
Classifier: Programming Language :: Python
Classifier: Programming Language :: Python :: 3
Classifier: Topic :: Security
Classifier: Topic :: Internet
Classifier: Topic :: Scientific/Engineering
Classifier: Topic :: System :: Distributed Computing
Classifier: Topic :: System :: Systems Administration :: Authentication/Directory
Classifier: Topic :: Software Development :: Libraries :: Python Modules
Requires-Dist: requests-oauthlib
Requires-Dist: six
Requires-Dist: PyOpenSSL
